antpack-0.4.dist-info/RECORD
antpack-0.4.dist-info/WHEEL
antpack-0.4.dist-info/entry_points.txt
antpack-0.4.dist-info/METADATA
antpack-0.4.dist-info/licenses/LICENSE
antpack/__init__.py
antpack/antpack_cpp_ext.cpython-310-darwin.so
antpack/antpack_license.py
antpack/antpack_cli.py
antpack/vj_tools/__init__.py
antpack/vj_tools/vj_gene_assignment.py
antpack/vj_tools/consensus_data/human_imgt_IGKJ_2025-03-14.fa.gz
antpack/vj_tools/consensus_data/mouse_imgt_IGKJ_2025-03-14.fa.gz
antpack/vj_tools/consensus_data/rabbit_imgt_IGKV_2025-03-14.fa.gz
antpack/vj_tools/consensus_data/mouse_imgt_TRAJ_2025-03-14.fa.gz
antpack/vj_tools/consensus_data/human_imgt_TRAJ_2025-03-14.fa.gz
antpack/vj_tools/consensus_data/mouse_imgt_TRDJ_2025-03-14.fa.gz
antpack/vj_tools/consensus_data/human_imgt_TRDJ_2025-03-14.fa.gz
antpack/vj_tools/consensus_data/human_imgt_IGLJ_2025-03-14.fa.gz
antpack/vj_tools/consensus_data/mouse_imgt_TRBJ_2025-03-14.fa.gz
antpack/vj_tools/consensus_data/human_imgt_TRBJ_2025-03-14.fa.gz
antpack/vj_tools/consensus_data/mouse_imgt_IGLJ_2025-03-14.fa.gz
antpack/vj_tools/consensus_data/rabbit_imgt_IGLV_2025-03-14.fa.gz
antpack/vj_tools/consensus_data/mouse_imgt_TRGJ_2025-03-14.fa.gz
antpack/vj_tools/consensus_data/human_imgt_TRGJ_2025-03-14.fa.gz
antpack/vj_tools/consensus_data/alpaca_imgt_IGHJ_2025-03-14.fa.gz
antpack/vj_tools/consensus_data/human_imgt_IGHJ_2025-03-14.fa.gz
antpack/vj_tools/consensus_data/mouse_imgt_IGHJ_2025-03-14.fa.gz
antpack/vj_tools/consensus_data/rabbit_imgt_IGHV_2025-03-14.fa.gz
antpack/vj_tools/consensus_data/mouse_imgt_TRBV_2025-03-14.fa.gz
antpack/vj_tools/consensus_data/human_imgt_IGLV_2025-03-14.fa.gz
antpack/vj_tools/consensus_data/mouse_imgt_IGLV_2025-03-14.fa.gz
antpack/vj_tools/consensus_data/human_imgt_TRBV_2025-03-14.fa.gz
antpack/vj_tools/consensus_data/rabbit_imgt_IGLJ_2025-03-14.fa.gz
antpack/vj_tools/consensus_data/mouse_imgt_TRGV_2025-03-14.fa.gz
antpack/vj_tools/consensus_data/human_imgt_TRGV_2025-03-14.fa.gz
antpack/vj_tools/consensus_data/alpaca_imgt_IGHV_2025-03-14.fa.gz
antpack/vj_tools/consensus_data/human_imgt_IGHV_2025-03-14.fa.gz
