Metadata-Version: 2.1
Name: antpack
Version: 0.4
Summary: A Python package for processing, manipulating and making inferences about antibody sequence data
Keywords: antibody,antibodies,antibody numbering,antibody humanization,antibody humanness,antibody analysis
Author-Email: Jonathan Parkinson <jlparkinson1@gmail.com>
License: Academic Software Licence (“ASL”)
Project-URL: Homepage, https://github.com/jlparkI/AntPack
Project-URL: Documentation, https://antpackdocumentationlatest.pages.dev/
Requires-Python: >=3.8
Requires-Dist: numpy
